LICENSE.txt
MANIFEST.in
README.rst
setup.py
pinogy_common/__init__.py
pinogy_common/admin.py
pinogy_common/cms_plugins.py
pinogy_common/models.py
pinogy_common/views.py
pinogy_common/widgets.py
pinogy_common.egg-info/PKG-INFO
pinogy_common.egg-info/SOURCES.txt
pinogy_common.egg-info/dependency_links.txt
pinogy_common.egg-info/not-zip-safe
pinogy_common.egg-info/requires.txt
pinogy_common.egg-info/top_level.txt
pinogy_common/static/css/admin/all-translations-mixin.css
pinogy_common/static/js/pinogy_common/jquery.knob.js
pinogy_common/static/js/pinogy_common/knob.js
pinogy_common/templates/pinogy_common/plugins/view_object_container.html