Metadata-Version: 1.1
Name: pinogy-common
Version: 0.0.9
Summary: Common utilities and code for Pinogy projects.
Home-page: https://bitbucket.org/pinogycorp/pgy-django-common
Author: Pinogy
Author-email: info@pinogy.com
License: LICENSE.txt
Platform: OS Independent
Classifier: Development Status :: 2 - Pre-Alpha
Classifier: Environment :: Web Environment
Classifier: Framework :: Django
Classifier: Intended Audience :: Developers
Classifier: License :: OSI Approved :: BSD License
Classifier: Operating System :: OS Independent
Classifier: Programming Language :: Python
Classifier: Topic :: Internet :: WWW/HTTP :: Dynamic Content
Classifier: Topic :: Software Development
Classifier: Topic :: Software Development :: Libraries :: Application Frameworks
